nitpyck/__init__.py
nitpyck/bsoup.py
nitpyck/google.py
nitpyck/gresult_info_retriever.py
nitpyck/html2text_formated.py
nitpyck/parse_search_terms.py
nitpyck/rx.py
nitpyck/util.py
nitpyck/venere.py
nitpyck/bak/bak_parse_search_terms.py
nitpyck/web/__init__.py
nitpyck/web/parsing_templates.py
nitpyck/web/url.py
nitpyck-0.0.3.dist-info/LICENSE
nitpyck-0.0.3.dist-info/METADATA
nitpyck-0.0.3.dist-info/WHEEL
nitpyck-0.0.3.dist-info/top_level.txt
nitpyck-0.0.3.dist-info/RECORD
