Metadata-Version: 2.1
Name: nitpyck
Version: 0.0.3
Summary: Utils for parsing.
Home-page: https://github.com/thorwhalen/newut/tree/master/nitpyck
Author: Thor Whalen
License: mit
Platform: any
License-File: LICENSE
